isodaterange/__init__.py
isodaterange-1.0.1.dist-info/LICENSE.md
isodaterange-1.0.1.dist-info/METADATA
isodaterange-1.0.1.dist-info/WHEEL
isodaterange-1.0.1.dist-info/top_level.txt
isodaterange-1.0.1.dist-info/RECORD
