Metadata-Version: 2.1
Name: isodaterange
Version: 1.0.1
Summary: Python module to convert an ISO date/time into a range
Home-page: https://github.com/antarctica/isodaterange
Author: Tim Barnes
Author-email: tdba@bas.ac.uk
License: Open Government License v3.0
Platform: UNKNOWN
Classifier: Development Status :: 5 - Production/Stable
Classifier: Intended Audience :: Developers
Classifier: License :: Other/Proprietary License
Classifier: Programming Language :: Python :: 3
Requires-Dist: isodate
